{"HOURLY_OBS_AND_FORCAST": {"_usage": "This data is restricted and may only be used with explicit permission from MetService NZ. Contact dataenquiries@metservice.com", "actualData": [{"date": "Mon 31 Oct 2016", "offset": 1, "rainFall": "0.0", "temperature": "7", "timeFrom": "02:00", "windDir": "calm", "windSpeed": "0"}, {"date": "Mon 31 Oct 2016", "offset": 2, "rainFall": "0.0", "temperature": "6", "timeFrom": "04:00", "windDir": "SW", "windSpeed": "4"}, {"date": "Mon 31 Oct 2016", "offset": 3, "rainFall": "0.0", "temperature": "6", "timeFrom": "06:00", "windDir": "S", "windSpeed": "6"}, {"date": "Mon 31 Oct 2016", "offset": 4, "rainFall": "0.0", "temperature": "9", "timeFrom": "08:00", "windDir": "S", "windSpeed": "4"}, {"date": "Mon 31 Oct 2016", "offset": 5, "rainFall": "0.0", "temperature": "14", "timeFrom": "10:00", "windDir": "SE", "windSpeed": "6"}, {"date": "Mon 31 Oct 2016", "offset": 6, "rainFall": "0.0", "temperature": "14", "timeFrom": "12:00", "windDir": "NE", "windSpeed": "9"}, {"date": "Mon 31 Oct 2016", "offset": 7, "rainFall": "0.0", "temperature": "14", "timeFrom": "14:00", "windDir": "N", "windSpeed": "15"}, {"date": "Mon 31 Oct 2016", "offset": 8, "rainFall": "0.0", "temperature": "16", "timeFrom": "16:00", "windDir": "N", "windSpeed": "17"}, {"date": "Mon 31 Oct 2016", "offset": 9, "rainFall": "0.0", "temperature": "15", "timeFrom": "18:00", "windDir": "N", "windSpeed": "17"}, {"date": "Mon 31 Oct 2016", "offset": 10, "rainFall": "0.0", "temperature": "14", "timeFrom": "20:00", "windDir": "NW", "windSpeed": "11"}], "dataPointCount": 49, "disclaimer": {"briefText": "The 2-hourly forecasts above are automatically generated by MetService's computer weather modelling system.", "fullText": "The 2-hourly forecasts above are automatically generated by MetService's computer weather modelling system. They have not been moderated by MetService's forecast team. The magnitude & timing of weather events (rain, changes in wind direction and speed) may differ from those described in worded forecasts. The rainfall data is given for the previous two hours. The forecast temperature & wind speed data have been adjusted to match the observation at the observation time, and progressively smaller adjustments towards none at 6 hours ahead of the observation time. Data generated for Tauranga Aero Automatic Weather Station(AWS-93186)."}, "forecastAws": "AWS-93186", "forecastData": [{"date": "Mon 31 Oct 2016", "offset": 11, "rainFall": "0.0", "temperature": "12", "timeFrom": "22:00", "windDir": "E", "windSpeed": "7"}, {"date": "Tue 01 Nov 2016", "offset": 12, "rainFall": "0.0", "temperature": "11", "timeFrom": "00:00", "windDir": "SE", "windSpeed": "6"}, {"date": "Tue 01 Nov 2016", "offset": 13, "rainFall": "0.0", "temperature": "9", "timeFrom": "02:00", "windDir": "S", "windSpeed": "6"}, {"date": "Tue 01 Nov 2016", "offset": 14, "rainFall": "0.2", "temperature": "8", "timeFrom": "04:00", "windDir": "S", "windSpeed": "6"}, {"date": "Tue 01 Nov 2016", "offset": 15, "rainFall": "0.0", "temperature": "8", "timeFrom": "06:00", "windDir": "S", "windSpeed": "6"}, {"date": "Tue 01 Nov 2016", "offset": 16, "rainFall": "0.0", "temperature": "11", "timeFrom": "08:00", "windDir": "S", "windSpeed": "4"}, {"date": "Tue 01 Nov 2016", "offset": 17, "rainFall": "0.0", "temperature": "15", "timeFrom": "10:00", "windDir": "N", "windSpeed": "7"}, {"date": "Tue 01 Nov 2016", "offset": 18, "rainFall": "0.0", "temperature": "15", "timeFrom": "12:00", "windDir": "N", "windSpeed": "11"}, {"date": "Tue 01 Nov 2016", "offset": 19, "rainFall": "0.0", "temperature": "16", "timeFrom": "14:00", "windDir": "N", "windSpeed": "15"}, {"date": "Tue 01 Nov 2016", "offset": 20, "rainFall": "0.0", "temperature": "16", "timeFrom": "16:00", "windDir": "N", "windSpeed": "17"}, {"date": "Tue 01 Nov 2016", "offset": 21, "rainFall": "0.0", "temperature": "16", "timeFrom": "18:00", "windDir": "NW", "windSpeed": "17"}, {"date": "Tue 01 Nov 2016", "offset": 22, "rainFall": "0.0", "temperature": "14", "timeFrom": "20:00", "windDir": "NW", "windSpeed": "13"}, {"date": "Tue 01 Nov 2016", "offset": 23, "rainFall": "0.0", "temperature": "14", "timeFrom": "22:00", "windDir": "NW", "windSpeed": "9"}, {"date": "Wed 02 Nov 2016", "offset": 24, "rainFall": "0.3", "temperature": "14", "timeFrom": "00:00", "windDir": "NW", "windSpeed": "11"}, {"date": "Wed 02 Nov 2016", "offset": 25, "rainFall": "0.2", "temperature": "14", "timeFrom": "02:00", "windDir": "NW", "windSpeed": "11"}, {"date": "Wed 02 Nov 2016", "offset": 26, "rainFall": "2.2", "temperature": "14", "timeFrom": "04:00", "windDir": "NW", "windSpeed": "13"}, {"date": "Wed 02 Nov 2016", "offset": 27, "rainFall": "1.5", "temperature": "14", "timeFrom": "06:00", "windDir": "NW", "windSpeed": "15"}, {"date": "Wed 02 Nov 2016", "offset": 28, "rainFall": "6.5", "temperature": "15", "timeFrom": "08:00", "windDir": "N", "windSpeed": "17"}, {"date": "Wed 02 Nov 2016", "offset": 29, "rainFall": "3.9", "temperature": "17", "timeFrom": "10:00", "windDir": "N", "windSpeed": "19"}, {"date": "Wed 02 Nov 2016", "offset": 30, "rainFall": "8.5", "temperature": "17", "timeFrom": "12:00", "windDir": "N", "windSpeed": "22"}, {"date": "Wed 02 Nov 2016", "offset": 31, "rainFall": "0.5", "temperature": "18", "timeFrom": "14:00", "windDir": "N", "windSpeed": "24"}, {"date": "Wed 02 Nov 2016", "offset": 32, "rainFall": "0.0", "temperature": "18", "timeFrom": "16:00", "windDir": "NW", "windSpeed": "20"}, {"date": "Wed 02 Nov 2016", "offset": 33, "rainFall": "0.0", "temperature": "17", "timeFrom": "18:00", "windDir": "W", "windSpeed": "24"}, {"date": "Wed 02 Nov 2016", "offset": 34, "rainFall": "0.0", "temperature": "15", "timeFrom": "20:00", "windDir": "W", "windSpeed": "22"}], "latestIssuedDate": "7:34pm Monday 31 Oct 2016", "localObsAws": "93186", "location": "Tauranga", "locationName": "Tauranga Aero Automatic Weather Station", "oneMinuteObsAws": "93186", "rainfallTotalForecast": 0.0, "rainfallTotalObserved": 0.0, "today": "Mon 31 Oct 2016", "windSrc": "EPD"}, "LOCAL_FORECAST": {"_usage": "This data is restricted and may only be used with explicit permission from MetService NZ. Contact dataenquiries@metservice.com", "days": [{"date": "31 Oct", "dow": "Monday", "dowTLA": "Mon", "forecast": "Fine breaks, chance shower. Dying sea breezes.", "forecastWord": "Partly cloudy", "issuedAt": "4:52pm 31 Oct", "max": "16", "min": "7", "riseSet": {"day": "31 October 2016", "id": "loc11050", "location": "Tauranga Aero AWS", "moonRise": "6:33am", "moonSet": "8:05pm", "sunRise": "6:09am", "sunSet": "7:49pm"}, "source": "IPS", "sourceTemps": "IPS"}, {"date": "1 Nov", "dow": "Tuesday", "dowTLA": "Tue", "forecast": "Cloud increasing, few showers from afternoon. Northerlies.", "forecastWord": "Few showers", "issuedAt": "4:52pm 31 Oct", "max": "17", "min": "12", "riseSet": {"day": "1 November 2016", "id": "loc11050", "location": "Tauranga Aero AWS", "moonRise": "7:07am", "moonSet": "8:59pm", "sunRise": "6:08am", "sunSet": "7:50pm"}, "source": "IPS", "sourceTemps": "IPS"}, {"date": "2 Nov", "dow": "Wednesday", "dowTLA": "Wed", "forecast": "AM rain, chance heavy, PM odd shower. Westerly change.", "forecastWord": "Few showers", "issuedAt": "10:51am 31 Oct", "max": "19", "min": "10", "riseSet": {"day": "2 November 2016", "id": "loc11050", "location": "Tauranga Aero AWS", "moonRise": "7:43am", "moonSet": "9:53pm", "sunRise": "6:07am", "sunSet": "7:51pm"}, "source": "IPS", "sourceTemps": "IPS"}, {"date": "3 Nov", "dow": "Thursday", "dowTLA": "Thu", "forecast": "Fine spells, but a few showers. Westerly winds.", "forecastWord": "Few showers", "issuedAt": "10:51am 31 Oct", "max": "19", "min": "10", "riseSet": {"day": "3 November 2016", "id": "loc11050", "location": "Tauranga Aero AWS", "moonRise": "8:23am", "moonSet": "10:45pm", "sunRise": "6:06am", "sunSet": "7:52pm"}, "source": "IPS", "sourceTemps": "IPS"}, {"date": "4 Nov", "dow": "Friday", "dowTLA": "Fri", "forecast": "Fine spells, risk shower. Westerlies.", "forecastWord": "Partly cloudy", "issuedAt": "10:51am 31 Oct", "max": "19", "min": "11", "riseSet": {"day": "4 November 2016", "id": "loc11050", "location": "Tauranga Aero AWS", "moonRise": "9:07am", "moonSet": "11:35pm", "sunRise": "6:05am", "sunSet": "7:53pm"}, "source": "IPS", "sourceTemps": "IPS"}, {"date": "5 Nov", "dow": "Saturday", "dowTLA": "Sat", "forecast": "Partly cloudy. Westerlies.", "forecastWord": "Partly cloudy", "issuedAt": "12:20pm 31 Oct", "max": "20", "min": "11", "riseSet": {"day": "5 November 2016", "id": "loc11050", "location": "Tauranga Aero AWS", "moonRise": "9:55am", "sunRise": "6:04am", "sunSet": "7:54pm"}, "source": "EC"}, {"date": "6 Nov", "dow": "Sunday", "dowTLA": "Sun", "forecast": "Fine with little wind.", "forecastWord": "Fine", "issuedAt": "12:20pm 31 Oct", "max": "21", "min": "12", "riseSet": {"day": "6 November 2016", "id": "loc11050", "location": "Tauranga Aero AWS", "moonRise": "10:46am", "moonSet": "12:22am", "sunRise": "6:03am", "sunSet": "7:56pm"}, "source": "EC"}, {"date": "7 Nov", "dow": "Monday", "dowTLA": "Mon", "forecast": "Showers. Northwesterlies.", "forecastWord": "Showers", "issuedAt": "12:20pm 31 Oct", "max": "20", "min": "12", "riseSet": {"day": "7 November 2016", "id": "loc11050", "location": "Tauranga Aero AWS", "moonRise": "11:42am", "moonSet": "1:07am", "sunRise": "6:02am", "sunSet": "7:57pm"}, "source": "EC"}, {"date": "8 Nov", "dow": "Tuesday", "dowTLA": "Tue", "forecast": "Showers. Westerlies.", "forecastWord": "Showers", "issuedAt": "12:20pm 31 Oct", "max": "21", "min": "13", "riseSet": {"day": "8 November 2016", "id": "loc11050", "location": "Tauranga Aero AWS", "moonRise": "12:41pm", "moonSet": "1:49am", "sunRise": "6:01am", "sunSet": "7:58pm"}, "source": "EC"}, {"date": "9 Nov", "dow": "Wednesday", "dowTLA": "Wed", "forecast": "Showers. Northwesterlies.", "forecastWord": "Showers", "issuedAt": "12:20pm 31 Oct", "max": "21", "min": "15", "riseSet": {"day": "9 November 2016", "id": "loc11050", "location": "Tauranga Aero AWS", "moonRise": "1:43pm", "moonSet": "2:28am", "sunRise": "6:00am", "sunSet": "7:59pm"}, "source": "EC"}], "locationECWasp": "TAURANGA", "locationGFS": "93186", "locationIPS": "TAURANGA", "locationWASP": "TAURANGA AERO AWS", "saturdayForecastWord": "Partly cloudy", "sundayForecastWord": "Fine"}, "TIDES": [{"days": [{"day": "2016 Oct 31", "dayOfWeek": "Mon", "tides": [{"height": "0.3", "time": "2:15am", "type": "LOW"}, {"height": "1.8", "time": "8:34am", "type": "HIGH"}, {"height": "0.4", "time": "2:33pm", "type": "LOW"}, {"height": "1.7", "time": "8:44pm", "type": "HIGH"}]}, {"day": "2016 Nov 1", "dayOfWeek": "Tue", "tides": [{"height": "0.3", "time": "2:55am", "type": "LOW"}, {"height": "1.8", "time": "9:14am", "type": "HIGH"}, {"height": "0.4", "time": "3:14pm", "type": "LOW"}, {"height": "1.7", "time": "9:23pm", "type": "HIGH"}]}, {"day": "2016 Nov 2", "dayOfWeek": "Wed", "tides": [{"height": "0.3", "time": "3:33am", "type": "LOW"}, {"height": "1.8", "time": "9:53am", "type": "HIGH"}, {"height": "0.4", "time": "3:53pm", "type": "LOW"}, {"height": "1.7", "time": "10:02pm", "type": "HIGH"}]}], "location": "Tauranga"}]}